PyYoubora-0.2.dist-info/METADATA
PyYoubora-0.2.dist-info/RECORD
PyYoubora-0.2.dist-info/WHEEL
PyYoubora-0.2.dist-info/top_level.txt
youbora/__init__.py
youbora/youbora_auth.py
youbora/youbora_client.py
