Metadata-Version: 2.1
Name: PyYoubora
Version: 0.2
Summary: Authentication library for amazing Python requests library against NPAW Youbora API.
Home-page: http://github.com/wieshka/PyYoubora
Author: Viesturs Proskins
Author-email: viesturs.proskins@gmail.com
License: UNKNOWN
Platform: UNKNOWN
Requires-Dist: requests
